ocr4all_pixel_classifier/__init__.py
ocr4all_pixel_classifier/lib/__init__.py
ocr4all_pixel_classifier/lib/architecture.py
ocr4all_pixel_classifier/lib/callback.py
ocr4all_pixel_classifier/lib/cc.py
ocr4all_pixel_classifier/lib/data_generator.py
ocr4all_pixel_classifier/lib/dataset.py
ocr4all_pixel_classifier/lib/evaluation.py
ocr4all_pixel_classifier/lib/image_ops.py
ocr4all_pixel_classifier/lib/layers.py
ocr4all_pixel_classifier/lib/metrics.py
ocr4all_pixel_classifier/lib/model.py
ocr4all_pixel_classifier/lib/network.py
ocr4all_pixel_classifier/lib/output.py
ocr4all_pixel_classifier/lib/pagexml.py
ocr4all_pixel_classifier/lib/pc_segmentation.py
ocr4all_pixel_classifier/lib/postprocess.py
ocr4all_pixel_classifier/lib/predictor.py
ocr4all_pixel_classifier/lib/predictor_data.py
ocr4all_pixel_classifier/lib/render.py
ocr4all_pixel_classifier/lib/trainer.py
ocr4all_pixel_classifier/lib/util.py
ocr4all_pixel_classifier/lib/xycut.py
ocr4all_pixel_classifier-0.6.6.data/data/requirements.txt
ocr4all_pixel_classifier-0.6.6.dist-info/LICENSE
ocr4all_pixel_classifier-0.6.6.dist-info/LICENSE.Apache-2.0
ocr4all_pixel_classifier-0.6.6.dist-info/LICENSE.GPL-3.0-or-later
ocr4all_pixel_classifier-0.6.6.dist-info/METADATA
ocr4all_pixel_classifier-0.6.6.dist-info/WHEEL
ocr4all_pixel_classifier-0.6.6.dist-info/top_level.txt
ocr4all_pixel_classifier-0.6.6.dist-info/RECORD
