Metadata-Version: 2.1
Name: ocr4all-pixel-classifier
Version: 0.6.6
Summary: UNKNOWN
Home-page: https://gitlab2.informatik.uni-wuerzburg.de/chw71yx/page-segmentation.git
Author: Christoph Wick, Alexander Hartelt, Alexander Gehrke
Author-email: christoph.wick@informatik.uni-wuerzburg.de, alexander.hartelt@informatik.uni-wuerzburg.de, alexander.gehrke@informatik.uni-wuerzburg.de
License: UNKNOWN
Keywords: OCR,page segmentation,pixel classifier
Platform: UNKNOWN
Classifier: Programming Language :: Python :: 3
Classifier: License :: OSI Approved :: GNU General Public License v3 or later (GPLv3+)
Classifier: License :: OSI Approved :: Apache Software License
Classifier: Intended Audience :: Science/Research
Classifier: Topic :: Scientific/Engineering :: Image Recognition
Requires-Dist: Pillow
Requires-Dist: numpy
Requires-Dist: scipy
Requires-Dist: scikit-image (~=0.17.2)
Requires-Dist: imageio (~=2.4.1)
Requires-Dist: tqdm
Requires-Dist: opencv-python-headless
Requires-Dist: dataclasses
Requires-Dist: efficientnet
Requires-Dist: lxml
Requires-Dist: ocr4all-pylib (>=0.2.0)
Requires-Dist: tensorflow (<=2.5.0,>=2.0.0)
